odoo/addons/fieldservice_recurring/README.rst
odoo/addons/fieldservice_recurring/__init__.py
odoo/addons/fieldservice_recurring/__manifest__.py
odoo/addons/fieldservice_recurring/data/ir_sequence.xml
odoo/addons/fieldservice_recurring/data/recurring_cron.xml
odoo/addons/fieldservice_recurring/models/__init__.py
odoo/addons/fieldservice_recurring/models/fsm_frequency.py
odoo/addons/fieldservice_recurring/models/fsm_frequency_set.py
odoo/addons/fieldservice_recurring/models/fsm_order.py
odoo/addons/fieldservice_recurring/models/fsm_recurring.py
odoo/addons/fieldservice_recurring/models/fsm_recurring_template.py
odoo/addons/fieldservice_recurring/readme/CONFIGURE.rst
odoo/addons/fieldservice_recurring/readme/CONTRIBUTORS.rst
odoo/addons/fieldservice_recurring/readme/CREDITS.rst
odoo/addons/fieldservice_recurring/readme/DESCRIPTION.rst
odoo/addons/fieldservice_recurring/readme/INSTALL.rst
odoo/addons/fieldservice_recurring/readme/ROADMAP.rst
odoo/addons/fieldservice_recurring/readme/USAGE.rst
odoo/addons/fieldservice_recurring/security/ir.model.access.csv
odoo/addons/fieldservice_recurring/security/recurring_security.xml
odoo/addons/fieldservice_recurring/security/res_groups.xml
odoo/addons/fieldservice_recurring/static/description/icon.png
odoo/addons/fieldservice_recurring/static/description/index.html
odoo/addons/fieldservice_recurring/views/fsm_frequency.xml
odoo/addons/fieldservice_recurring/views/fsm_frequency_set.xml
odoo/addons/fieldservice_recurring/views/fsm_recurring.xml
odoo/addons/fieldservice_recurring/views/fsm_recurring_template.xml
odoo11_addon_fieldservice_recurring-11.0.0.1.1.99.dev6.dist-info/METADATA
odoo11_addon_fieldservice_recurring-11.0.0.1.1.99.dev6.dist-info/WHEEL
odoo11_addon_fieldservice_recurring-11.0.0.1.1.99.dev6.dist-info/top_level.txt
odoo11_addon_fieldservice_recurring-11.0.0.1.1.99.dev6.dist-info/RECORD
